karrio/mappers/yanwen/__init__.py
karrio/mappers/yanwen/mapper.py
karrio/mappers/yanwen/proxy.py
karrio/mappers/yanwen/settings.py
karrio/providers/yanwen/__init__.py
karrio/providers/yanwen/tracking.py
karrio/providers/yanwen/units.py
karrio/providers/yanwen/utils.py
karrio.yanwen-2023.4.dist-info/METADATA
karrio.yanwen-2023.4.dist-info/WHEEL
karrio.yanwen-2023.4.dist-info/top_level.txt
karrio.yanwen-2023.4.dist-info/RECORD
